meggie_reproduction/__init__.py
meggie_reproduction/configuration.json
meggie_reproduction/actions/__init__.py
meggie_reproduction/actions/reproduction_run/__init__.py
meggie_reproduction/actions/reproduction_run/configuration.json
meggie_reproduction/actions/reproduction_run/dialogs/runActionsDialogMain.py
meggie_reproduction/actions/reproduction_run/dialogs/runActionsDialogUi.py
meggie_reproduction/actions/reproduction_run/dialogs/runActionsDialogUi.ui
meggie_reproduction/actions/reproduction_run/tests/__init__.py
meggie_reproduction/actions/reproduction_run/tests/actions.json
meggie_reproduction/actions/reproduction_run/tests/test_reproduction_run.py
meggie_reproduction-0.1.2.dist-info/METADATA
meggie_reproduction-0.1.2.dist-info/WHEEL
meggie_reproduction-0.1.2.dist-info/top_level.txt
meggie_reproduction-0.1.2.dist-info/RECORD
