Metadata-Version: 2.4
Name: meggie_reproduction
Version: 0.1.2
Summary: Reproduction plugin for Meggie
License: BSD
Project-URL: homepage, https://github.com/cibr-jyu/meggie_reproduction
Requires-Dist: meggie>=1.9.2
Provides-Extra: dev
Requires-Dist: black; extra == "dev"
Requires-Dist: pylama; extra == "dev"
Requires-Dist: pytest; extra == "dev"
Requires-Dist: pytest-qt; extra == "dev"
Requires-Dist: build; extra == "dev"
Requires-Dist: twine; extra == "dev"
Requires-Dist: setuptools; extra == "dev"
Provides-Extra: test
Requires-Dist: black; extra == "test"
Requires-Dist: pylama; extra == "test"
Requires-Dist: pytest; extra == "test"
Requires-Dist: pytest-qt; extra == "test"
Requires-Dist: setuptools; extra == "test"
